{
  "SUHI_Day_Change_mean": 0.7931382754802326,
  "SUHI_Day_Change_std": 1.034088572369284,
  "SUHI_Day_Change_min": -0.6678740992784924,
  "SUHI_Day_Change_max": 2.336889737566402,
  "cities_with_valid_data": 6,
  "SUHI_Night_Change_mean": 0.5673628799827787,
  "SUHI_Night_Change_std": 0.5434449262274031,
  "SUHI_Night_Change_min": -0.3427480652041943,
  "SUHI_Night_Change_max": 1.240489920336552,
  "analysis_type": "multi_dataset_suhi",
  "method": "combined_urban_classification",
  "warm_months": [
    6,
    7,
    8
  ],
  "analysis_scale_m": 1000,
  "urban_threshold": 0.15,
  "rural_threshold": 0.2,
  "min_urban_pixels": 3,
  "min_rural_pixels": 10,
  "ring_width_km": 25,
  "cities_analyzed": 6,
  "cities_with_valid_suhi": 6,
  "analysis_span_years": 6,
  "first_period": "2018",
  "last_period": "2024"
}